LICENSE
README.md
setup.cfg
setup.py
teampy/__init__.py
teampy/command_line_rat.py
teampy/command_line_setup.py
teampy/core.py
teampy/latex_preamble.tex
teampy/latex_preamble_old.tex
teampy/rat-box.pdf
teampy/scratch.pdf
teampy.egg-info/PKG-INFO
teampy.egg-info/SOURCES.txt
teampy.egg-info/dependency_links.txt
teampy.egg-info/entry_points.txt
teampy.egg-info/requires.txt
teampy.egg-info/top_level.txt