Metadata-Version: 2.1
Name: teampy
Version: 0.2.0
Summary: Tools for Team-Based Learning
Home-page: https://github.com/falkr/teampy
Download-URL: https://github.com/falkr/teampy/archive/0.2.tar.gz
Author: Frank Alexander Kraemer
Author-email: kraemer.frank@gmail.com
License: GPLv3
Keywords: education
Classifier: Development Status :: 3 - Alpha
Classifier: Intended Audience :: Education
Classifier: Programming Language :: Python :: 3
Classifier: Programming Language :: Python :: 3.3
Classifier: Programming Language :: Python :: 3.4
Classifier: Programming Language :: Python :: 3.5
Classifier: Programming Language :: Python :: 3.6
Classifier: Programming Language :: Python :: 3.7
Classifier: Programming Language :: Python :: 3.8
Classifier: Programming Language :: Python :: 3.10
License-File: LICENSE
